README
setup.py
udd.py
python_udd.egg-info/PKG-INFO
python_udd.egg-info/SOURCES.txt
python_udd.egg-info/dependency_links.txt
python_udd.egg-info/top_level.txt