Metadata-Version: 1.0
Name: python-udd
Version: 0.1
Summary: SQLAlchemy bindings for Ultimate Debian Database
Home-page: http://www.github.com/irl/python-udd
Author: Iain R. Learmonth
Author-email: irl@debian.org
License: BSD
Platform: UNKNOWN
